{
	"info": {
		"_postman_id": "990def49-5f98-4080-9930-9f30a5c5faf4",
		"name": "mern20PostmanConfig",
		"schema": "https://schema.getpostman.com/json/collection/v2.1.0/collection.json"
	},
	"item": [
		{
			"name": "getPosts > 200",
			"request": {
				"method": "GET",
				"header": [],
				"body": {},
				"url": {
					"raw": "http://localhost:5000/posts",
					"protocol": "http",
					"host": [
						"localhost"
					],
					"port": "5000",
					"path": [
						"posts"
					]
				}
			},
			"response": []
		}
	]
}